test/WorkWeixinClientTest.py
test/__init__.py
work_weixin_api/__init__.py
work_weixin_api/version.py
work_weixin_api/work_weixin_api.py
work_weixin_api/work_weixin_client.py
work_weixin_api-0.0.3.dist-info/METADATA
work_weixin_api-0.0.3.dist-info/WHEEL
work_weixin_api-0.0.3.dist-info/top_level.txt
work_weixin_api-0.0.3.dist-info/zip-safe
work_weixin_api-0.0.3.dist-info/RECORD
