Metadata-Version: 2.1
Name: work-weixin-api
Version: 0.0.3
Summary: 企业微信接口封装库
Home-page: https://github.com/mouday/work-weixin-api
Author: Peng Shiyu
Author-email: pengshiyuyx@gmail.com
License: MIT
Keywords: work,weixin
Platform: UNKNOWN
Classifier: Programming Language :: Python :: 3.7
Requires-Dist: session-request
Requires-Dist: environs
Requires-Dist: mo-cache
